texterrors_align.cpython-312-i386-linux-musl.so
texterrors/texterrors.py
texterrors/__init__.py
texterrors-1.0.9.dist-info/top_level.txt
texterrors-1.0.9.dist-info/METADATA
texterrors-1.0.9.dist-info/LICENSE
texterrors-1.0.9.dist-info/RECORD
texterrors-1.0.9.dist-info/entry_points.txt
texterrors-1.0.9.dist-info/WHEEL
texterrors.libs/libgcc_s-f3fb5a36.so.1
texterrors.libs/libstdc++-d2a021ba.so.6.0.32
