Metadata-Version: 2.4
Name: texterrors
Version: 1.0.9
Summary: For WER
Home-page: https://github.com/RuABraun/texterrors
Author: Rudolf A Braun
Author-email: rab014@gmail.com
License: Apache-2.0 License
Requires-Python: >=3.6
License-File: LICENSE
Requires-Dist: pybind11
Requires-Dist: plac
Requires-Dist: numpy
Requires-Dist: loguru
Requires-Dist: termcolor
Requires-Dist: Levenshtein
Requires-Dist: regex
Requires-Dist: pytest
Dynamic: author
Dynamic: author-email
Dynamic: description
Dynamic: description-content-type
Dynamic: home-page
Dynamic: license
Dynamic: license-file
Dynamic: requires-dist
Dynamic: requires-python
Dynamic: summary
